{
  "appName": "Shelf Sync",
  "fontFamily": "Sora",
  "colors": {
    "primary": "#10B981",
    "secondary": "#F59E0B",
    "background": "#F0F9F5",
    "accent": "#6366F1"
  },
  "icons": [
    "alert-triangle",
    "battery",
    "bell",
    "bookmark",
    "camera",
    "check",
    "chef-hat",
    "chevron-down",
    "chevron-right",
    "chevron-up",
    "clock",
    "file-text",
    "help-circle",
    "home",
    "layout-grid",
    "list",
    "log-out",
    "mic",
    "moon",
    "package",
    "plus",
    "search",
    "settings",
    "shield",
    "sliders-horizontal",
    "sun",
    "tag",
    "trending-down",
    "wifi",
    "zap"
  ],
  "fonts": [],
  "iconCount": 30,
  "fontFileCount": 0
}
